{
    "PlpMain": {
        "Project": "collectValuableToys",
        "Name": "navigate",
        "Type": "Glue",
        "Version": 1.0
    },
    "GlueFramework": "ROS",
    "ModuleResponse": {
        "ResponseRules": [
            {
                "Response": "eSuccess",
                "ConditionCodeWithLocalVariables": "skillSuccess2"
            },
            {
                "Response": "eFailed",
                "ConditionCodeWithLocalVariables": "True"
            }
        ]
    },
    "ModuleActivation": {
        "RosService": {
            "ImportCode": [
                {
                    "From": "geometry_msgs.msg",
                    "Import": [
                        "Point"
                    ]
                },
                {
                    "From": "task3_env.srv",
                    "Import": [
                        "navigate",
                        "navigateResponse"
                    ]
                }
            ],
            "ServicePath": "/navigate",
            "ServiceName": "navigate",
            "ServiceParameters": [
                {
                    "ServiceFieldName": "location",
                    "AssignServiceFieldCode": "destination"
                }
            ]
        }
    },
    "LocalVariablesInitialization": [
        {
            "LocalVariableName": "skillSuccess2",
            "VariableType":"bool",
            "FromROSServiceResponse": true,
			"AssignmentName": "",
            "AssignmentCode": ["skillSuccess2=__input.success"],
            "ImportCode": [
                {
                    "From": "std_msgs.msg",
                    "Import": [
                        "Bool"
                    ]
                }
            ]
        }, 
        {
            "InputLocalVariable": "destination",
            "FromGlobalVariable": "oDestination"
        }
    ]
}
